{
  "success": true,
  "timestamp": "2026-01-11T00:00:00Z",
  "endpoints": {
    "repo": "https://deepseekoracle.github.io/Excavationpro/lygo-repo.json",
    "updates": "https://deepseekoracle.github.io/Excavationpro/LYGO-Network/updatefeed.json",
    "champions": "https://deepseekoracle.github.io/Excavationpro/lygo-data.json",
    "network": "https://deepseekoracle.github.io/Excavationpro/lygo-data-two.json"
  },
  "status": {
    "repo_online": true,
    "api_version": "1.618",
    "last_checked": "2026-01-11T00:00:00Z"
  }
}
